fsscan/__init__.py
fsscan/__main__.py
fsscan/__version__.py
fsscan/callbacks.py
fsscan/cli.py
fsscan/core.py
fsscan-0.0.5.dist-info/LICENSE
fsscan-0.0.5.dist-info/METADATA
fsscan-0.0.5.dist-info/WHEEL
fsscan-0.0.5.dist-info/entry_points.txt
fsscan-0.0.5.dist-info/top_level.txt
fsscan-0.0.5.dist-info/RECORD
