Metadata-Version: 2.1
Name: fsscan
Version: 0.0.5
Summary: Directory scanner
Home-page: https://github.com/krakozaure/fsscan
Author: krakozaure
Author-email: 
License: MIT
Platform: UNKNOWN
Classifier: License :: OSI Approved :: MIT License
Classifier: Operating System :: OS Independent
Classifier: Programming Language :: Python :: 3.4
Classifier: Programming Language :: Python :: 3.5
Classifier: Programming Language :: Python :: 3.6
Classifier: Programming Language :: Python :: 3.7
Classifier: Programming Language :: Python :: 3 :: Only
Classifier: Environment :: Console
Classifier: Topic :: System :: Filesystems
Classifier: Topic :: Terminals
Classifier: Topic :: Utilities
License-File: LICENSE
Requires-Dist: scandir ; python_version == "3.4"
